odoo10_addon_stock_packaging_calculator-10.0.1.0.1-py3.8-nspkg.pth
odoo/addons/stock_packaging_calculator/README.rst
odoo/addons/stock_packaging_calculator/__init__.py
odoo/addons/stock_packaging_calculator/__manifest__.py
odoo/addons/stock_packaging_calculator/context.py
odoo/addons/stock_packaging_calculator/i18n/stock_packaging_calculator.pot
odoo/addons/stock_packaging_calculator/models/__init__.py
odoo/addons/stock_packaging_calculator/models/product.py
odoo/addons/stock_packaging_calculator/readme/CONTRIBUTORS.rst
odoo/addons/stock_packaging_calculator/readme/DESCRIPTION.rst
odoo/addons/stock_packaging_calculator/readme/ROADMAP.rst
odoo/addons/stock_packaging_calculator/readme/USAGE.rst
odoo/addons/stock_packaging_calculator/static/description/icon.png
odoo/addons/stock_packaging_calculator/static/description/index.html
odoo/addons/stock_packaging_calculator/tests/__init__.py
odoo/addons/stock_packaging_calculator/tests/test_context.py
odoo/addons/stock_packaging_calculator/tests/test_packaging_calc.py
odoo10_addon_stock_packaging_calculator-10.0.1.0.1.dist-info/METADATA
odoo10_addon_stock_packaging_calculator-10.0.1.0.1.dist-info/WHEEL
odoo10_addon_stock_packaging_calculator-10.0.1.0.1.dist-info/namespace_packages.txt
odoo10_addon_stock_packaging_calculator-10.0.1.0.1.dist-info/top_level.txt
odoo10_addon_stock_packaging_calculator-10.0.1.0.1.dist-info/RECORD
